celestial_tools/__init__.py
celestial_tools/strings.py
celestial_tools/client/__init__.py
celestial_tools/client/dual_rootfs_update_cmdline.py
celestial_tools/client/rootfs/__init__.py
celestial_tools/client/system/__init__.py
celestial_tools/client/system/cmdline.py
celestial_tools-0.0.7.dist-info/LICENSE
celestial_tools-0.0.7.dist-info/METADATA
celestial_tools-0.0.7.dist-info/WHEEL
celestial_tools-0.0.7.dist-info/entry_points.txt
celestial_tools-0.0.7.dist-info/top_level.txt
celestial_tools-0.0.7.dist-info/RECORD
